[{"ItemType":1,"ItemID":"gift100","Nume":"CADOU ZILNIC","Pret":0,"Imagine":"https://cdn.discordapp.com/attachments/1008571099497377792/1067649569246154783/Zeeekk_a_clock_as_mystery_box_casino_chips_prize_prize_shining__e785cf32-ac23-438d-98a6-9e197677c4ab.png","Descriere":"Contine unul din urmatoarele 50Puncte, 100Puncte, 250Puncte. POTI DESCHIDE 1 PE ZI!","Stoc":1,"RequireAditional":false,"OnlyMembers":false,"IsVisible":true,"Cooldown":1440.0,"OptionalData":null,"CooldownValue":0.0,"Drops":[{"Name":"10points","Luck":25,"DropType":2,"DropList":"10"},{"Name":"25points","Luck":70,"DropType":2,"DropList":"25"},{"Name":"100points","Luck":5,"DropType":2,"DropList":"100"}]},{"ItemType":0,"ItemID":"super50","Nume":"50 RON SUPERBET","Pret":100,"Imagine":"https://cdn.discordapp.com/attachments/1008571099497377792/1067641346237669469/Zeeekk_mystery_box_casino_chips_prize_prize_shining_crown_life__7d6940f0-2d7b-4f35-a5dd-88b814c7961a.png","Descriere":"50 RON SUPERBET RULAJ X1","Stoc":5,"RequireAditional":false,"OnlyMembers":true,"IsVisible":true,"Cooldown":25.0,"OptionalData":null,"CooldownValue":0.0,"Drops":[]},{"ItemType":1,"ItemID":"MysteryBox","Nume":"Mystery Box","Pret":100,"Imagine":"https://cdn.discordapp.com/attachments/1008571099497377792/1067642073316077628/Zeeekk_mystery_box_casino_chips_prize_prize_shining_crown_life__8b775ab8-242c-4c53-83af-cf6828868236.png","Descriere":"","Stoc":9,"RequireAditional":false,"OnlyMembers":false,"IsVisible":true,"Cooldown":0.2,"OptionalData":null,"CooldownValue":0.0,"Drops":[{"Name":"50 RON SHINING","Luck":25,"DropType":0,"DropList":"50 RON SHINING"},{"Name":"Necastigator","Luck":25,"DropType":0,"DropList":"Necastigator"}]},{"ItemType":1,"ItemID":"SuperMystery","Nume":"Super Mystery Box","Pret":250,"Imagine":"https://cdn.midjourney.com/9e870810-b5ff-429c-9b1a-9c21302cae52/grid_0.png","Descriere":"ADS","Stoc":10,"RequireAditional":false,"OnlyMembers":true,"IsVisible":true,"Cooldown":0.2,"OptionalData":null,"CooldownValue":0.0,"Drops":[{"Name":"50 RON SHINING","Luck":85,"DropType":0,"DropList":"50 RON SHINING"},{"Name":"100 RON SHINING","Luck":10,"DropType":0,"DropList":"100 RON SHINING"},{"Name":"150 RON SHINING","Luck":5,"DropType":0,"DropList":"150 RON SHINING"}]}]